backtracepython/__init__.py
backtracepython/client.py
backtracepython/report.py
backtracepython/report_queue.py
backtracepython/request_handler.py
backtracepython/source_code_handler.py
backtracepython/utils.py
backtracepython/version.py
backtracepython/attributes/__init__.py
backtracepython/attributes/attribute_manager.py
backtracepython/attributes/attribute_provider.py
backtracepython/attributes/backtrace_attribute_provider.py
backtracepython/attributes/linux_memory_attribute_provider.py
backtracepython/attributes/machineId_attribute_provider.py
backtracepython/attributes/machine_attribute_provider.py
backtracepython/attributes/process_attribute_provider.py
backtracepython/attributes/report_data_builder.py
backtracepython/attributes/session_attribute_provider.py
backtracepython/attributes/system_attribute_provider.py
backtracepython/attributes/user_attribute_provider.py
backtracepython-0.4.2.dist-info/licenses/LICENSE
example/__init__.py
example/example.py
tests/__init__.py
tests/test_basic_flow.py
tests/test_client_attributes.py
tests/test_report_attributes.py
tests/test_stack_trace_parser.py
tests/test_submission_url.py
backtracepython-0.4.2.dist-info/METADATA
backtracepython-0.4.2.dist-info/WHEEL
backtracepython-0.4.2.dist-info/top_level.txt
backtracepython-0.4.2.dist-info/RECORD
