Metadata-Version: 2.4
Name: backtracepython
Version: 0.4.2
Summary: Backtrace.io error reporting tool for Python
Home-page: https://github.com/backtrace-labs/backtrace-python
Author: Backtrace.io
Author-email: team@backtrace.io
License: MIT
Project-URL: Homepage, https://backtrace.io
Project-URL: Source, https://github.com/backtrace-labs/backtrace-python
Project-URL: Changelog, https://github.com/backtrace-labs/backtrace-python/blob/master/CHANGELOG.md
Project-URL: Documentation, https://docs.saucelabs.com/error-reporting/language-integrations/python/
Classifier: Intended Audience :: Developers
Classifier: Intended Audience :: System Administrators
Classifier: License :: OSI Approved :: MIT License
Classifier: Operating System :: OS Independent
Classifier: Topic :: Software Development :: Libraries :: Python Modules
Classifier: Topic :: Software Development :: Bug Tracking
Classifier: Topic :: System :: Monitoring
Classifier: Environment :: Console
Classifier: Environment :: Web Environment
Classifier: Programming Language :: Python :: 2.7
Classifier: Programming Language :: Python :: 3
Classifier: Programming Language :: Python :: 3.7
Classifier: Programming Language :: Python :: 3.8
Classifier: Programming Language :: Python :: 3.9
Classifier: Programming Language :: Python :: 3.10
Requires-Python: >=2.7, !=3.0.*, !=3.1.*, !=3.2.*, !=3.3.*, !=3.4.*, <4
License-File: LICENSE
Requires-Dist: six
Requires-Dist: simplejson
Requires-Dist: requests
Provides-Extra: test
Requires-Dist: pytest; extra == "test"
Dynamic: author
Dynamic: author-email
Dynamic: classifier
Dynamic: description
Dynamic: description-content-type
Dynamic: home-page
Dynamic: license
Dynamic: license-file
Dynamic: project-url
Dynamic: provides-extra
Dynamic: requires-dist
Dynamic: requires-python
Dynamic: summary
